py_package/__init__.py
py_package/temperature.py
publish_pypi_package-0.1.3.dist-info/LICENSE
publish_pypi_package-0.1.3.dist-info/METADATA
publish_pypi_package-0.1.3.dist-info/WHEEL
publish_pypi_package-0.1.3.dist-info/top_level.txt
publish_pypi_package-0.1.3.dist-info/RECORD
