Metadata-Version: 2.1
Name: publish_pypi_package
Version: 0.1.3
Summary: A conversion package
Author: Refael
Author-email: beker.refael@gmail.com
License: MIT
Keywords: conversion
Classifier: Development Status :: 3 - Alpha
Classifier: Intended Audience :: Developers
Classifier: Programming Language :: Python :: 3
License-File: LICENSE
